README.md
setup.cfg
setup.py
protobix/__init__.py
protobix/datacontainer.py
protobix/sampleprobe.py
protobix/senderprotocol.py
protobix/zabbixagentconfig.py
protobix.egg-info/PKG-INFO
protobix.egg-info/SOURCES.txt
protobix.egg-info/dependency_links.txt
protobix.egg-info/requires.txt
protobix.egg-info/top_level.txt