Metadata-Version: 1.1
Name: protobix
Version: 1.0.2
Summary: Implementation of Zabbix Sender protocol
Home-page: https://github.com/jbfavre/python-protobix/
Author: Jean Baptiste Favre
Author-email: jean-baptiste.favre@blablacar.com
License: GPL-3+
Download-URL: https://github.com/jbfavre/python-protobix/archive/1.0.2.tar.gz
Keywords: monitoring,zabbix,trappers
Platform: UNKNOWN
